pygeoroc/__init__.py
pygeoroc/__main__.py
pygeoroc/api.py
pygeoroc/db.py
pygeoroc/errata.py
pygeoroc/commands/__init__.py
pygeoroc/commands/check.py
pygeoroc/commands/createdb.py
pygeoroc/commands/download.py
pygeoroc/commands/ls.py
pygeoroc/commands/stats.py
pygeoroc-2.0.0.dist-info/LICENSE
pygeoroc-2.0.0.dist-info/METADATA
pygeoroc-2.0.0.dist-info/WHEEL
pygeoroc-2.0.0.dist-info/entry_points.txt
pygeoroc-2.0.0.dist-info/top_level.txt
pygeoroc-2.0.0.dist-info/RECORD
