Metadata-Version: 2.1
Name: pygeoroc
Version: 2.0.0
Summary: programmatic access to GEOROC data
Home-page: https://github.com/pofatu/pygeoroc
Author: Robert Forkel
Author-email: robert_forkel@eva.mpg.de
License: Apache 2.0
Keywords: data
Platform: any
Classifier: Programming Language :: Python
Classifier: Programming Language :: Python :: 3
Classifier: Programming Language :: Python :: 3.7
Classifier: Programming Language :: Python :: 3.8
Classifier: Programming Language :: Python :: 3.9
Classifier: Programming Language :: Python :: 3.10
Requires-Python: >=3.7
Requires-Dist: attrs (>=19.3)
Requires-Dist: clldutils (>=3.5)
Requires-Dist: csvw
Requires-Dist: requests
Requires-Dist: tqdm
Provides-Extra: dev
Requires-Dist: flake8 ; extra == 'dev'
Requires-Dist: twine ; extra == 'dev'
Requires-Dist: wheel ; extra == 'dev'
Provides-Extra: test
Requires-Dist: coverage (>=4.2) ; extra == 'test'
Requires-Dist: pytest-cov ; extra == 'test'
Requires-Dist: pytest-mock ; extra == 'test'
Requires-Dist: pytest (>=4.3) ; extra == 'test'
Requires-Dist: requests-mock ; extra == 'test'
